commerce_trust_score/__init__.py
commerce_trust_score/__version__.py
commerce_trust_score/agent.py
commerce_trust_score/client.py
commerce_trust_score/config.py
commerce_trust_score/http_client.py
commerce_trust_score/models.py
commerce_trust_score/py.typed
commerce_trust_score/tools.py
e_commerce_trust_score-0.1.0.dist-info/licenses/LICENSE
e_commerce_trust_score-0.1.0.dist-info/METADATA
e_commerce_trust_score-0.1.0.dist-info/WHEEL
e_commerce_trust_score-0.1.0.dist-info/top_level.txt
e_commerce_trust_score-0.1.0.dist-info/RECORD
