Metadata-Version: 2.4
Name: e-commerce-trust-score
Version: 0.1.0
Summary: A Python client library for analyzing URL trust scores using AI-powered analysis
Author-email: Vivian Li <vivian@example.com>
License: MIT
Project-URL: Homepage, https://github.com/yourusername/e-commerce-trust-score
Project-URL: Documentation, https://github.com/yourusername/e-commerce-trust-score#readme
Project-URL: Repository, https://github.com/yourusername/e-commerce-trust-score
Project-URL: Issues, https://github.com/yourusername/e-commerce-trust-score/issues
Keywords: trust-score,url-analysis,security,claude,ai,mcp
Classifier: Development Status :: 3 - Alpha
Classifier: Intended Audience :: Developers
Classifier: License :: OSI Approved :: MIT License
Classifier: Programming Language :: Python :: 3
Classifier: Programming Language :: Python :: 3.10
Classifier: Programming Language :: Python :: 3.11
Classifier: Programming Language :: Python :: 3.12
Classifier: Programming Language :: Python :: 3.13
Classifier: Topic :: Security
Classifier: Topic :: Software Development :: Libraries :: Python Modules
Requires-Python: >=3.10
License-File: LICENSE
Requires-Dist: claude-agent-sdk>=0.1.0
Requires-Dist: anyio>=4.0.0
Requires-Dist: pydantic>=2.0.0
Requires-Dist: python-dotenv>=1.0.0
Requires-Dist: httpx>=0.25.0
Provides-Extra: dev
Requires-Dist: pytest>=7.0.0; extra == "dev"
Requires-Dist: pytest-asyncio>=0.21.0; extra == "dev"
Requires-Dist: pytest-cov>=4.0.0; extra == "dev"
Requires-Dist: black>=23.0.0; extra == "dev"
Requires-Dist: ruff>=0.1.0; extra == "dev"
Requires-Dist: mypy>=1.0.0; extra == "dev"
Provides-Extra: server
Requires-Dist: fastapi>=0.104.0; extra == "server"
Requires-Dist: uvicorn[standard]>=0.24.0; extra == "server"
Dynamic: license-file
